{
"type": "FeatureCollection",
"name": "owls",
"crs": { "type": "name", "properties": { "name": "urn:ogc:def:crs:OGC:1.3:CRS84" } },
"features": [
{ "type": "Feature", "properties": { "site_id": "site_1", "lat": -41.767495, "lon": 145.507035 }, "geometry": { "type": "Point", "coordinates": [ 145.507035, -41.767495 ] } },
{ "type": "Feature", "properties": { "site_id": "site_3", "lat": -41.76752, "lon": 145.51228 }, "geometry": { "type": "Point", "coordinates": [ 145.51228, -41.76752 ] } },
{ "type": "Feature", "properties": { "site_id": "site_4", "lat": -41.77204, "lon": 145.51394 }, "geometry": { "type": "Point", "coordinates": [ 145.51394, -41.77204 ] } },
{ "type": "Feature", "properties": { "site_id": "site_5", "lat": -41.77314, "lon": 145.50706 }, "geometry": { "type": "Point", "coordinates": [ 145.50706, -41.77314 ] } },
{ "type": "Feature", "properties": { "site_id": "site_6", "lat": -41.7564, "lon": 145.50792 }, "geometry": { "type": "Point", "coordinates": [ 145.50792, -41.7564 ] } }
]
}
